ParticleSwarmOptimization/Particle.py
ParticleSwarmOptimization/Swarm.py
ParticleSwarmOptimization/__init__.py
ParticleSwarmOptimization-1.0.3.dist-info/LICENSE.txt
ParticleSwarmOptimization-1.0.3.dist-info/METADATA
ParticleSwarmOptimization-1.0.3.dist-info/WHEEL
ParticleSwarmOptimization-1.0.3.dist-info/top_level.txt
ParticleSwarmOptimization-1.0.3.dist-info/RECORD
